blueprint/__init__.py
blueprint/cli.py
blueprint/core.py
blueprint_cli-0.1.0.dist-info/licenses/LICENSE
blueprint_cli-0.1.0.dist-info/METADATA
blueprint_cli-0.1.0.dist-info/WHEEL
blueprint_cli-0.1.0.dist-info/entry_points.txt
blueprint_cli-0.1.0.dist-info/top_level.txt
blueprint_cli-0.1.0.dist-info/RECORD
