Metadata-Version: 2.4
Name: blueprint-cli
Version: 0.1.0
Summary: A modern CLI tool to generate clean folder structure.
Author-email: Harsh Raval <mrharshrraval@gmail.com>
License: MIT
Requires-Python: >=3.8
License-File: LICENSE
Dynamic: license-file
